sigfox_manager/__init__.py
sigfox_manager/sigfox_manager.py
sigfox_manager/models/schemas.py
sigfox_manager/sigfox_manager_exceptions/__init__.py
sigfox_manager/sigfox_manager_exceptions/sigfox_exceptions.py
sigfox_manager/utils/http_utils.py
sigfox_manager-0.3.0.dist-info/licenses/LICENSE
sigfox_manager-0.3.0.dist-info/METADATA
sigfox_manager-0.3.0.dist-info/WHEEL
sigfox_manager-0.3.0.dist-info/top_level.txt
sigfox_manager-0.3.0.dist-info/RECORD
