Metadata-Version: 2.4
Name: sigfox-manager
Version: 0.3.0
Summary: A Python library for handling Sigfox API operations
Home-page: https://github.com/Jobenas/sigfox_manager_utility
Author: Jorge Benavides Aspiazu
Author-email: Jorge Benavides Aspiazu <jobenas@gmail.com>
License: MIT License
Project-URL: Homepage, https://github.com/Jobenas/sigfox_manager_utility
Project-URL: Repository, https://github.com/Jobenas/sigfox_manager_utility
Project-URL: Documentation, https://github.com/Jobenas/sigfox_manager_utility#readme
Project-URL: Bug Tracker, https://github.com/Jobenas/sigfox_manager_utility/issues
Keywords: sigfox,api,iot,device,management
Classifier: Development Status :: 3 - Alpha
Classifier: Intended Audience :: Developers
Classifier: License :: OSI Approved :: MIT License
Classifier: Operating System :: OS Independent
Classifier: Programming Language :: Python :: 3
Classifier: Programming Language :: Python :: 3.8
Classifier: Programming Language :: Python :: 3.9
Classifier: Programming Language :: Python :: 3.10
Classifier: Programming Language :: Python :: 3.11
Classifier: Programming Language :: Python :: 3.12
Classifier: Topic :: Software Development :: Libraries :: Python Modules
Classifier: Topic :: Communications
Requires-Python: >=3.8
License-File: LICENSE
Requires-Dist: requests>=2.25.0
Requires-Dist: pydantic>=1.8.0
Provides-Extra: dev
Requires-Dist: pytest>=6.0; extra == "dev"
Requires-Dist: pytest-cov>=2.0; extra == "dev"
Requires-Dist: black>=21.0; extra == "dev"
Requires-Dist: flake8>=3.8; extra == "dev"
Requires-Dist: mypy>=0.800; extra == "dev"
Requires-Dist: build>=0.7.0; extra == "dev"
Requires-Dist: twine>=3.4.0; extra == "dev"
Dynamic: author
Dynamic: home-page
Dynamic: license-file
Dynamic: requires-python
